{
    "local_variable": {
        "744165377": {
            "variable_dict": {}, 
            "variable_length_dict": {}
        }, 
        "1851621378": {
            "variable_dict": {}, 
            "variable_length_dict": {}
        }
    }, 
    "trigger_dict": {
        "744165377": {
            "action": [
                {
                    "action_type": "PRINT_MESSAGE_ACTION_TO_DIALOG", 
                    "args_list": [
                        {
                            "arg_type": 100175, 
                            "args_list": [
                                3
                            ], 
                            "sub_type": 1
                        }, 
                        {
                            "arg_type": 100003, 
                            "args_list": [
                                "\u83b7\u5f97\u706b\u70e7\u8fde\u8425"
                            ], 
                            "sub_type": 1
                        }
                    ], 
                    "bp": false, 
                    "element_id": 744165377000004, 
                    "enable": true
                }
            ], 
            "call_enabled": true, 
            "condition": [], 
            "enabled": true, 
            "event": [
                {
                    "args_list": [], 
                    "element_id": 744165377000001, 
                    "enable": true, 
                    "event_type": "ABILITY_OBTAIN"
                }
            ], 
            "group_id": 134258927, 
            "p_trigger_id": null, 
            "trigger_id": 744165377, 
            "trigger_name": "\u65b0\u5efa\u89e6\u53d1\u5668", 
            "valid": true, 
            "var_data": [
                {}, 
                {}, 
                []
            ]
        }, 
        "1851621378": {
            "action": [], 
            "call_enabled": true, 
            "condition": [], 
            "enabled": true, 
            "event": [
                {
                    "args_list": [], 
                    "element_id": 1851621378000002, 
                    "enable": true, 
                    "event_type": "ABILITY_LEVEL_CHANGED"
                }
            ], 
            "group_id": 134258927, 
            "p_trigger_id": null, 
            "trigger_id": 1851621378, 
            "trigger_name": "\u65b0\u5efa\u89e6\u53d1\u5668_2", 
            "valid": true, 
            "var_data": [
                {}, 
                {}, 
                []
            ]
        }
    }, 
    "trigger_group_info": [
        {
            "_trigger_group_": true, 
            "group": [
                {
                    "__tuple__": true, 
                    "items": [
                        744165377, 
                        "\u65b0\u5efa\u89e6\u53d1\u5668"
                    ]
                }, 
                {
                    "__tuple__": true, 
                    "items": [
                        1851621378, 
                        "\u65b0\u5efa\u89e6\u53d1\u5668_2"
                    ]
                }
            ], 
            "key": 134258927, 
            "name": "134258927"
        }
    ], 
    "trigger_version": "1.2", 
    "variable_dict": {}, 
    "variable_group_info": [], 
    "variable_length_dict": {}
}