{
    "custom": true, 
    "effect_keep": false, 
    "effect_max_boundingbox": [
        -9.531919479370117, 
        -14.547224044799805, 
        -9.676485061645508, 
        9.531919479370117, 
        14.493183135986328, 
        9.168740272521973
    ], 
    "effect_max_life": 1.0, 
    "effect_path": "Fx_Effect/OtherType/Fx_Skill/Knife/0da27309-5baf-4d45-bfc9-cc39024a8976", 
    "is_beam_effect": false, 
    "meshes": [], 
    "model_id": 134276289, 
    "name": "\u6a59\u8272\u5200\u5149_2"
}