{
    "adapt_mode": 2, 
    "anim_data": {}, 
    "children": [
        {
            "adapter_option": [
                false, 
                false, 
                false, 
                false, 
                -3.9375, 
                -3.9375, 
                -15.749, 
                -9.751
            ], 
            "cap_insets": {
                "__tuple__": true, 
                "items": [
                    496.0, 
                    272.0, 
                    496.0, 
                    272.0
                ]
            }, 
            "children": [], 
            "color": {
                "__tuple__": true, 
                "items": [
                    96, 
                    80, 
                    60, 
                    255
                ]
            }, 
            "event_list": [], 
            "image": 134247453, 
            "name": "image_8", 
            "open_adapter": true, 
            "pos_data": {
                "__tuple__": true, 
                "items": [
                    957.001, 
                    540.0, 
                    49.8438, 
                    50.0, 
                    0, 
                    0
                ]
            }, 
            "prefab_sub_key": null, 
            "scene_ui_name": null, 
            "size": {
                "__tuple__": true, 
                "items": [
                    1945.5, 
                    1087.875
                ]
            }, 
            "type": 4, 
            "uid": "399b1f2c-f51c-4803-a5d7-d5538085e104"
        }, 
        {
            "adapter_option": [
                false, 
                false, 
                false, 
                false, 
                0.0003, 
                -8.0003, 
                -25.0, 
                -25.0
            ], 
            "cap_insets": {
                "__tuple__": true, 
                "items": [
                    640.0, 
                    360.0, 
                    640.0, 
                    360.0
                ]
            }, 
            "children": [
                {
                    "adapter_option": [
                        false, 
                        false, 
                        false, 
                        false, 
                        136.2221, 
                        851.7779, 
                        1615.0002, 
                        254.9998
                    ], 
                    "children": [], 
                    "event_list": [], 
                    "font": {
                        "__tuple__": true, 
                        "items": [
                            "HKWeiBeiW7", 
                            24
                        ]
                    }, 
                    "font_color": {
                        "__tuple__": true, 
                        "items": [
                            213, 
                            201, 
                            159, 
                            255
                        ]
                    }, 
                    "name": "\u65f6\u95f4", 
                    "open_adapter": true, 
                    "pos_data": {
                        "__tuple__": true, 
                        "items": [
                            1665.0002, 
                            901.7779, 
                            84.5178, 
                            82.884, 
                            0, 
                            0
                        ]
                    }, 
                    "prefab_sub_key": null, 
                    "scene_ui_name": null, 
                    "text": {
                        "__tuple__": true, 
                        "items": [
                            "", 
                            false
                        ]
                    }, 
                    "type": 15, 
                    "uid": "3e8ab663-d079-42be-bee2-5cd24efbbe4a"
                }, 
                {
                    "adapter_option": [
                        false, 
                        false, 
                        false, 
                        false, 
                        809.3789, 
                        147.3787, 
                        858.4994, 
                        756.5006
                    ], 
                    "children": [], 
                    "event_list": [
                        {
                            "action_list": [], 
                            "enabled": true, 
                            "name": "\u80dc\u5229-\u8fd4\u56de\u5927\u5385", 
                            "not_wait_network": false, 
                            "sound_id": null, 
                            "type": 30
                        }
                    ], 
                    "name": "\u80dc\u5229-\u8fd4\u56de\u5927\u5385", 
                    "normal_picture": 134273356, 
                    "open_adapter": true, 
                    "pos_data": {
                        "__tuple__": true, 
                        "items": [
                            1035.9994, 
                            212.9999, 
                            52.5888, 
                            19.5772, 
                            0, 
                            0
                        ]
                    }, 
                    "prefab_sub_key": null, 
                    "scene_ui_name": null, 
                    "size": {
                        "__tuple__": true, 
                        "items": [
                            355.0, 
                            131.2424
                        ]
                    }, 
                    "touch_scale": {
                        "__tuple__": true, 
                        "items": [
                            0.95, 
                            0.95
                        ]
                    }, 
                    "type": 1, 
                    "uid": "e492bf6c-dca7-4c0f-a17c-5b6327d128a2"
                }, 
                {
                    "adapter_option": [
                        false, 
                        false, 
                        false, 
                        false, 
                        -282.3315, 
                        -169.83, 
                        -403.1762, 
                        778.8238
                    ], 
                    "cap_insets": {
                        "__tuple__": true, 
                        "items": [
                            373.0, 
                            360.0, 
                            373.0, 
                            360.0
                        ]
                    }, 
                    "children": [], 
                    "event_list": [], 
                    "image": 134229396, 
                    "name": "\u9646\u900a\u80dc\u5229\u7ed3\u7b97", 
                    "open_adapter": true, 
                    "pos_data": {
                        "__tuple__": true, 
                        "items": [
                            394.0, 
                            600.2507, 
                            20.0, 
                            55.1701, 
                            0, 
                            0
                        ]
                    }, 
                    "prefab_sub_key": null, 
                    "scene_ui_name": null, 
                    "size": {
                        "__tuple__": true, 
                        "items": [
                            1594.3524, 
                            1540.1615
                        ]
                    }, 
                    "type": 4, 
                    "uid": "79505249-d518-407e-a4ef-3188c633e657"
                }, 
                {
                    "cap_insets": {
                        "__tuple__": true, 
                        "items": [
                            373.0, 
                            360.0, 
                            373.0, 
                            360.0
                        ]
                    }, 
                    "children": [], 
                    "event_list": [], 
                    "image": 134243702, 
                    "name": "\u5415\u8499\u80dc\u5229\u7ed3\u7b97", 
                    "pos_data": {
                        "__tuple__": true, 
                        "items": [
                            393.3616, 
                            594.4241, 
                            19.9676, 
                            54.6346, 
                            0, 
                            0
                        ]
                    }, 
                    "prefab_sub_key": null, 
                    "scene_ui_name": null, 
                    "size": {
                        "__tuple__": true, 
                        "items": [
                            1612.3735, 
                            1557.5701
                        ]
                    }, 
                    "type": 4, 
                    "uid": "0f534d98-ba2a-4a92-a269-4a0367ca9d66"
                }, 
                {
                    "cap_insets": {
                        "__tuple__": true, 
                        "items": [
                            373.0, 
                            360.0, 
                            373.0, 
                            360.0
                        ]
                    }, 
                    "children": [], 
                    "event_list": [], 
                    "image": 134236633, 
                    "name": "\u5b59\u6743\u80dc\u5229\u7ed3\u7b97", 
                    "pos_data": {
                        "__tuple__": true, 
                        "items": [
                            400.9994, 
                            594.0001, 
                            20.3553, 
                            54.5956, 
                            0, 
                            0
                        ]
                    }, 
                    "prefab_sub_key": null, 
                    "scene_ui_name": null, 
                    "size": {
                        "__tuple__": true, 
                        "items": [
                            1597.2377, 
                            1542.9488
                        ]
                    }, 
                    "type": 4, 
                    "uid": "41f325d3-c136-4bc7-8699-5dece925566a"
                }, 
                {
                    "cap_insets": {
                        "__tuple__": true, 
                        "items": [
                            373.0, 
                            360.0, 
                            373.0, 
                            360.0
                        ]
                    }, 
                    "children": [], 
                    "event_list": [], 
                    "image": 134227869, 
                    "name": "\u5927\u4e54\u80dc\u5229\u7ed3\u7b97", 
                    "pos_data": {
                        "__tuple__": true, 
                        "items": [
                            400.0624, 
                            593.545, 
                            20.3077, 
                            54.5538, 
                            0, 
                            0
                        ]
                    }, 
                    "prefab_sub_key": null, 
                    "scene_ui_name": null, 
                    "size": {
                        "__tuple__": true, 
                        "items": [
                            1598.8684, 
                            1544.524
                        ]
                    }, 
                    "type": 4, 
                    "uid": "f9226ab1-1f02-40ea-ba39-98313bf38154"
                }, 
                {
                    "cap_insets": {
                        "__tuple__": true, 
                        "items": [
                            373.0, 
                            360.0, 
                            373.0, 
                            360.0
                        ]
                    }, 
                    "children": [], 
                    "event_list": [], 
                    "image": 134271578, 
                    "name": "\u5c0f\u4e54\u80dc\u5229\u7ed3\u7b97", 
                    "pos_data": {
                        "__tuple__": true, 
                        "items": [
                            397.2552, 
                            593.2534, 
                            20.1652, 
                            54.527, 
                            0, 
                            0
                        ]
                    }, 
                    "prefab_sub_key": null, 
                    "scene_ui_name": null, 
                    "size": {
                        "__tuple__": true, 
                        "items": [
                            1614.0651, 
                            1559.2042
                        ]
                    }, 
                    "type": 4, 
                    "uid": "74d3183c-da13-4e57-8f25-6e2232a86904"
                }, 
                {
                    "cap_insets": {
                        "__tuple__": true, 
                        "items": [
                            373.0, 
                            360.0, 
                            373.0, 
                            360.0
                        ]
                    }, 
                    "children": [], 
                    "event_list": [], 
                    "image": 134218193, 
                    "name": "\u5468\u745c\u80dc\u5229\u7ed3\u7b97", 
                    "pos_data": {
                        "__tuple__": true, 
                        "items": [
                            397.2229, 
                            592.6515, 
                            20.1636, 
                            54.4716, 
                            0, 
                            0
                        ]
                    }, 
                    "prefab_sub_key": null, 
                    "scene_ui_name": null, 
                    "size": {
                        "__tuple__": true, 
                        "items": [
                            1613.0, 
                            1558.1753
                        ]
                    }, 
                    "type": 4, 
                    "uid": "879866be-b2ca-440e-9ef4-73823eaf8c4b"
                }, 
                {
                    "children": [], 
                    "event_list": [], 
                    "font": {
                        "__tuple__": true, 
                        "items": [
                            "HKSongW9", 
                            24
                        ]
                    }, 
                    "font_color": {
                        "__tuple__": true, 
                        "items": [
                            190, 
                            174, 
                            140, 
                            255
                        ]
                    }, 
                    "name": "\u8d26\u53f7\u6635\u79f01", 
                    "pos_data": {
                        "__tuple__": true, 
                        "items": [
                            1108.9994, 
                            820.0005, 
                            56.2944, 
                            75.3677, 
                            0, 
                            0
                        ]
                    }, 
                    "prefab_sub_key": null, 
                    "scene_ui_name": null, 
                    "size": {
                        "__tuple__": true, 
                        "items": [
                            172.0, 
                            100.0
                        ]
                    }, 
                    "text": {
                        "__tuple__": true, 
                        "items": [
                            "\u6211\u6709\u957f\u957f\u7684\u540d\u5b57", 
                            false
                        ]
                    }, 
                    "type": 3, 
                    "uid": "082b77d6-5557-45d3-b4db-864df1317a4c"
                }, 
                {
                    "children": [], 
                    "event_list": [], 
                    "font": {
                        "__tuple__": true, 
                        "items": [
                            "HKSongW9", 
                            24
                        ]
                    }, 
                    "font_color": {
                        "__tuple__": true, 
                        "items": [
                            190, 
                            174, 
                            140, 
                            255
                        ]
                    }, 
                    "name": "\u5e10\u53f7\u6635\u79f03", 
                    "pos_data": {
                        "__tuple__": true, 
                        "items": [
                            1108.9994, 
                            555.0181, 
                            56.2944, 
                            51.0127, 
                            0, 
                            0
                        ]
                    }, 
                    "prefab_sub_key": null, 
                    "scene_ui_name": null, 
                    "size": {
                        "__tuple__": true, 
                        "items": [
                            172.0, 
                            100.0
                        ]
                    }, 
                    "text": {
                        "__tuple__": true, 
                        "items": [
                            "\u6211\u6709\u957f\u957f\u7684\u540d\u5b57", 
                            false
                        ]
                    }, 
                    "type": 3, 
                    "uid": "4b43627f-1b56-4dee-ac22-ea2fad39a085"
                }, 
                {
                    "children": [], 
                    "event_list": [], 
                    "font": {
                        "__tuple__": true, 
                        "items": [
                            "HKSongW9", 
                            24
                        ]
                    }, 
                    "font_color": {
                        "__tuple__": true, 
                        "items": [
                            190, 
                            174, 
                            140, 
                            255
                        ]
                    }, 
                    "name": "\u5e10\u53f7\u6635\u79f04", 
                    "pos_data": {
                        "__tuple__": true, 
                        "items": [
                            1108.9994, 
                            415.0178, 
                            56.2944, 
                            38.145, 
                            0, 
                            0
                        ]
                    }, 
                    "prefab_sub_key": null, 
                    "scene_ui_name": null, 
                    "size": {
                        "__tuple__": true, 
                        "items": [
                            172.0, 
                            100.0
                        ]
                    }, 
                    "text": {
                        "__tuple__": true, 
                        "items": [
                            "\u6211\u6709\u957f\u957f\u7684\u540d\u5b57", 
                            false
                        ]
                    }, 
                    "type": 3, 
                    "uid": "70de9b65-a5f0-4a14-9983-5f3b69aa926b"
                }, 
                {
                    "children": [], 
                    "event_list": [], 
                    "font": {
                        "__tuple__": true, 
                        "items": [
                            "HKSongW9", 
                            24
                        ]
                    }, 
                    "font_color": {
                        "__tuple__": true, 
                        "items": [
                            190, 
                            174, 
                            140, 
                            255
                        ]
                    }, 
                    "name": "\u5e10\u53f7\u6635\u79f02", 
                    "pos_data": {
                        "__tuple__": true, 
                        "items": [
                            1108.9994, 
                            683.2001, 
                            56.2944, 
                            62.7941, 
                            0, 
                            0
                        ]
                    }, 
                    "prefab_sub_key": null, 
                    "scene_ui_name": null, 
                    "size": {
                        "__tuple__": true, 
                        "items": [
                            172.0, 
                            100.0
                        ]
                    }, 
                    "text": {
                        "__tuple__": true, 
                        "items": [
                            "\u6211\u6709\u957f\u957f\u7684\u540d\u5b57", 
                            false
                        ]
                    }, 
                    "type": 3, 
                    "uid": "8c19f9a7-6faa-431f-847c-74e5eb8fa4b5"
                }, 
                {
                    "children": [], 
                    "event_list": [], 
                    "font": {
                        "__tuple__": true, 
                        "items": [
                            "HKSongW9", 
                            18
                        ]
                    }, 
                    "font_color": {
                        "__tuple__": true, 
                        "items": [
                            155, 
                            155, 
                            155, 
                            255
                        ]
                    }, 
                    "name": "input_field_3", 
                    "pos_data": {
                        "__tuple__": true, 
                        "items": [
                            1317.0006, 
                            772.0009, 
                            66.8528, 
                            70.956, 
                            0, 
                            0
                        ]
                    }, 
                    "prefab_sub_key": null, 
                    "scene_ui_name": null, 
                    "size": {
                        "__tuple__": true, 
                        "items": [
                            587.2727, 
                            100.0
                        ]
                    }, 
                    "text": {
                        "__tuple__": true, 
                        "items": [
                            "", 
                            false
                        ]
                    }, 
                    "type": 15, 
                    "uid": "516731a2-4dd9-4bee-bad2-3491d35bf4c5"
                }, 
                {
                    "children": [], 
                    "event_list": [], 
                    "font": {
                        "__tuple__": true, 
                        "items": [
                            "HKSongW9", 
                            18
                        ]
                    }, 
                    "font_color": {
                        "__tuple__": true, 
                        "items": [
                            155, 
                            155, 
                            155, 
                            255
                        ]
                    }, 
                    "name": "input_field_3_1", 
                    "pos_data": {
                        "__tuple__": true, 
                        "items": [
                            1317.0006, 
                            641.3997, 
                            66.8528, 
                            58.9522, 
                            0, 
                            0
                        ]
                    }, 
                    "prefab_sub_key": null, 
                    "scene_ui_name": null, 
                    "size": {
                        "__tuple__": true, 
                        "items": [
                            587.2727, 
                            100.0
                        ]
                    }, 
                    "text": {
                        "__tuple__": true, 
                        "items": [
                            "", 
                            false
                        ]
                    }, 
                    "type": 15, 
                    "uid": "30819090-09a3-4dc7-b536-995149cf001d"
                }, 
                {
                    "children": [], 
                    "event_list": [], 
                    "font": {
                        "__tuple__": true, 
                        "items": [
                            "HKSongW9", 
                            18
                        ]
                    }, 
                    "font_color": {
                        "__tuple__": true, 
                        "items": [
                            155, 
                            155, 
                            155, 
                            255
                        ]
                    }, 
                    "name": "input_field_3_2", 
                    "pos_data": {
                        "__tuple__": true, 
                        "items": [
                            1317.0006, 
                            508.4334, 
                            66.8528, 
                            46.731, 
                            0, 
                            0
                        ]
                    }, 
                    "prefab_sub_key": null, 
                    "scene_ui_name": null, 
                    "size": {
                        "__tuple__": true, 
                        "items": [
                            587.2727, 
                            100.0
                        ]
                    }, 
                    "text": {
                        "__tuple__": true, 
                        "items": [
                            "", 
                            false
                        ]
                    }, 
                    "type": 15, 
                    "uid": "c52fa98e-0f23-4f5e-8f42-5ff94b3f061f"
                }, 
                {
                    "children": [], 
                    "event_list": [], 
                    "font": {
                        "__tuple__": true, 
                        "items": [
                            "HKSongW9", 
                            18
                        ]
                    }, 
                    "font_color": {
                        "__tuple__": true, 
                        "items": [
                            155, 
                            155, 
                            155, 
                            255
                        ]
                    }, 
                    "name": "input_field_3_3", 
                    "pos_data": {
                        "__tuple__": true, 
                        "items": [
                            1317.0006, 
                            366.1002, 
                            66.8528, 
                            33.6489, 
                            0, 
                            0
                        ]
                    }, 
                    "prefab_sub_key": null, 
                    "scene_ui_name": null, 
                    "size": {
                        "__tuple__": true, 
                        "items": [
                            587.2727, 
                            100.0
                        ]
                    }, 
                    "text": {
                        "__tuple__": true, 
                        "items": [
                            "", 
                            false
                        ]
                    }, 
                    "type": 15, 
                    "uid": "9dbdb7d4-1918-4430-b3c2-1567b6e6dec5"
                }
            ], 
            "event_list": [], 
            "image": 134227088, 
            "name": "image_26", 
            "open_adapter": true, 
            "pos_data": {
                "__tuple__": true, 
                "items": [
                    960.0, 
                    535.9997, 
                    50.0, 
                    49.6296, 
                    0, 
                    0
                ]
            }, 
            "prefab_sub_key": null, 
            "scene_ui_name": null, 
            "size": {
                "__tuple__": true, 
                "items": [
                    1970.0, 
                    1088.0
                ]
            }, 
            "type": 4, 
            "uid": "733ea801-8c24-4835-92f3-f58179e068d0"
        }
    ], 
    "name": "win", 
    "opacity": 1.0, 
    "type": 2, 
    "ui_anims": [], 
    "uid": "d4c01f64-7413-4c8e-b0e5-4297d4a59c7a", 
    "visible": false, 
    "zorder": 400
}